LICENSE.txt
README.md
setup.cfg
setup.py
scrapy_scraping_link/__init__.py
scrapy_scraping_link/middleware.py
scrapy_scraping_link/request.py
scrapy_scraping_link/spider.py
scrapy_scraping_link.egg-info/PKG-INFO
scrapy_scraping_link.egg-info/SOURCES.txt
scrapy_scraping_link.egg-info/dependency_links.txt
scrapy_scraping_link.egg-info/requires.txt
scrapy_scraping_link.egg-info/top_level.txt