Metadata-Version: 2.1
Name: scrapy-scraping-link
Version: 0.0.8
Summary: Scrapy middleware for Scraping.link
Home-page: https://github.com/nicolasmarin/scrapy-scraping-link
Author: Nicolas Marin
Author-email: info@scraping.link
License: MIT
Download-URL: https://github.com/nicolasmarin/scrapy-scraping-link/archive/refs/heads/main.zip
Keywords: web scraping,scraping,proxy rotating,html
Platform: UNKNOWN
Classifier: License :: OSI Approved :: MIT License
Classifier: Programming Language :: Python
Classifier: Programming Language :: Python :: 3
Classifier: Programming Language :: Python :: 3.5
Classifier: Programming Language :: Python :: 3.6
Classifier: Framework :: Scrapy
Classifier: Topic :: Software Development :: Libraries :: Application Frameworks
Classifier: Topic :: Software Development :: Libraries :: Python Modules
Requires-Python: >=3.5
